fv3grid/C192_grid_spec.tile1.nc
fv3grid/C192_grid_spec.tile2.nc
fv3grid/C192_grid_spec.tile3.nc
fv3grid/C192_grid_spec.tile4.nc
fv3grid/C192_grid_spec.tile5.nc
fv3grid/C192_grid_spec.tile6.nc
fv3grid/C384_grid_spec.tile1.nc
fv3grid/C384_grid_spec.tile2.nc
fv3grid/C384_grid_spec.tile3.nc
fv3grid/C384_grid_spec.tile4.nc
fv3grid/C384_grid_spec.tile5.nc
fv3grid/C384_grid_spec.tile6.nc
fv3grid/C48_grid_spec.tile1.nc
fv3grid/C48_grid_spec.tile2.nc
fv3grid/C48_grid_spec.tile3.nc
fv3grid/C48_grid_spec.tile4.nc
fv3grid/C48_grid_spec.tile5.nc
fv3grid/C48_grid_spec.tile6.nc
fv3grid/C768_grid_spec.tile1.nc
fv3grid/C768_grid_spec.tile2.nc
fv3grid/C768_grid_spec.tile3.nc
fv3grid/C768_grid_spec.tile4.nc
fv3grid/C768_grid_spec.tile5.nc
fv3grid/C768_grid_spec.tile6.nc
fv3grid/C96_grid_spec.tile1.nc
fv3grid/C96_grid_spec.tile2.nc
fv3grid/C96_grid_spec.tile3.nc
fv3grid/C96_grid_spec.tile4.nc
fv3grid/C96_grid_spec.tile5.nc
fv3grid/C96_grid_spec.tile6.nc
fv3grid/__init__.py
fv3grid-1.0.1.dist-info/LICENSE
fv3grid-1.0.1.dist-info/METADATA
fv3grid-1.0.1.dist-info/WHEEL
fv3grid-1.0.1.dist-info/top_level.txt
fv3grid-1.0.1.dist-info/RECORD
