Metadata-Version: 2.1
Name: fv3grid
Version: 1.0.1
Summary: FV3 Grid Data
Home-page: https://github.com/noaa-oar-arl/fv3grid
Author: Barry D. Baker
Author-email: barry.baker@noaa.gov
Maintainer: Barry D. Baker
Maintainer-email: barry.baker@noaa.gov
License: MIT
Keywords: fv3gfs
Platform: UNKNOWN
License-File: LICENSE
